README.md
setup.cfg
setup.py
PyWatermark/_WExceptions.py
PyWatermark/__init__.py
PyWatermark/_constants.py
PyWatermark/_fontMap.py
PyWatermark/watermark.py
PyWatermark.egg-info/PKG-INFO
PyWatermark.egg-info/SOURCES.txt
PyWatermark.egg-info/dependency_links.txt
PyWatermark.egg-info/requires.txt
PyWatermark.egg-info/top_level.txt
PyWatermark/fonts/Bangers-Regular.ttf
PyWatermark/fonts/MerriweatherSans-Regular.ttf
PyWatermark/fonts/Oswald-Regular.ttf
PyWatermark/fonts/Raleway-Regular.ttf
PyWatermark/fonts/Roboto-Regular.ttf
tests/__init__.py