Metadata-Version: 2.1
Name: PyWatermark
Version: 0.1.4
Summary: A library to watermark your images easily.
Home-page: https://github.com/ieshaan12/watermark
Author: Ieshaan Saxena
Author-email: ieshaan1999@gmail.com
License: MIT
Download-URL: https://github.com/ieshaan12/watermark/archive/v0.1.4.tar.gz
Platform: UNKNOWN
Classifier: Development Status :: 5 - Production/Stable
Classifier: Natural Language :: English
Classifier: Programming Language :: Python :: 3
Classifier: License :: OSI Approved :: MIT License
Classifier: Operating System :: OS Independent
